pycef/__init__.py
pycef-1.11.dist-info/LICENSE
pycef-1.11.dist-info/METADATA
pycef-1.11.dist-info/WHEEL
pycef-1.11.dist-info/top_level.txt
pycef-1.11.dist-info/zip-safe
pycef-1.11.dist-info/RECORD
