Metadata-Version: 2.1
Name: pycef
Version: 1.11
Summary: A very simple CEF parser.
Home-page: https://github.com/DavidJBianco/pycef
Author: David J. Bianco
Author-email: davidjbianco@gmail.com
License: MIT
Keywords: cef,parser,CEF
Platform: UNKNOWN
Classifier: Programming Language :: Python :: 3
Classifier: Programming Language :: Python :: 2
Classifier: Programming Language :: Python :: 3.7
Classifier: Programming Language :: Python :: 2.7
Classifier: License :: OSI Approved :: MIT License
Requires-Dist: future
